xgrammar/__init__.py
xgrammar/base.py
xgrammar/compiler.py
xgrammar/config.py
xgrammar/exception.py
xgrammar/grammar.py
xgrammar/matcher.py
xgrammar/testing.py
xgrammar/tokenizer_info.py
xgrammar/xgrammar_bindings.cpython-312-x86_64-linux-gnu.so
xgrammar/contrib/__init__.py
xgrammar/contrib/hf.py
xgrammar/contrib/mlxlm.py
xgrammar/kernels/__init__.py
xgrammar/kernels/apply_token_bitmask_inplace_cpu.py
xgrammar/kernels/apply_token_bitmask_inplace_cuda.cu
xgrammar/kernels/apply_token_bitmask_inplace_cuda.py
xgrammar/kernels/apply_token_bitmask_inplace_torch_compile.py
xgrammar/kernels/apply_token_bitmask_inplace_triton.py
xgrammar/kernels/apply_token_bitmask_mlx.py
xgrammar/support/__init__.py
xgrammar/support/logging.py
b10_xgrammar-0.1.22.dist-info/METADATA
b10_xgrammar-0.1.22.dist-info/WHEEL
b10_xgrammar-0.1.22.dist-info/RECORD
b10_xgrammar-0.1.22.dist-info/licenses/LICENSE
b10_xgrammar-0.1.22.dist-info/licenses/NOTICE
