Metadata-Version: 2.1
Name: b10-xgrammar
Version: 0.1.22
Summary: Efficient, Flexible and Portable Structured Generation
Keywords: machine learning,inference
Author: MLC Team
License: Apache 2.0
Classifier: License :: OSI Approved :: Apache Software License
Classifier: Development Status :: 4 - Beta
Classifier: Intended Audience :: Developers
Classifier: Intended Audience :: Education
Classifier: Intended Audience :: Science/Research
Project-URL: Homepage, https://xgrammar.mlc.ai/
Project-URL: GitHub, https://github.com/mlc-ai/xgrammar
Requires-Python: <4,>=3.8
Requires-Dist: pydantic
Requires-Dist: torch>=1.10.0
Requires-Dist: transformers>=4.38.0
Requires-Dist: triton; platform_system == "Linux" and platform_machine == "x86_64"
Requires-Dist: mlx-lm; platform_system == "Darwin" and platform_machine == "arm64"
Requires-Dist: ninja
Requires-Dist: numpy
Requires-Dist: typing-extensions>=4.9.0
Provides-Extra: test
Requires-Dist: huggingface-hub[cli]; extra == "test"
Requires-Dist: protobuf; extra == "test"
Requires-Dist: pytest; extra == "test"
Requires-Dist: sentencepiece; extra == "test"
Requires-Dist: tiktoken; extra == "test"
Requires-Dist: transformers<4.50.0; platform_system == "Darwin" and extra == "test"
